Metadata-Version: 1.0
Name: tiktokproj
Version: 1.1
Summary: Game to play tik tok with computer
Home-page: http://www.tiktokprojpackage.com/
Author: Raushan
Author-email: items4all@yahoo.co.uk
License: "Home"
Platform: UNKNOWN
